[{"comparison_object": "tellership", "suggestions": []}, {"comparison_object": "telly", "suggestions": []}, {"comparison_object": "tellies", "suggestions": []}, {"comparison_object": "tellieses", "suggestions": []}, {"comparison_object": "telligraph", "suggestions": []}, {"comparison_object": "tellima", "suggestions": []}, {"comparison_object": "tellin", "suggestions": []}, {"comparison_object": "tellina", "suggestions": []}, {"comparison_object": "tellinacea", "suggestions": []}, {"comparison_object": "tellinacean", "suggestions": []}, {"comparison_object": "tellinaceous", "suggestions": []}, {"comparison_object": "telling", "suggestions": ["showing", "asking", "tattling", "lying", "coaching", "trying", "discovering"]}, {"comparison_object": "tellingly", "suggestions": []}, {"comparison_object": "tellinidae", "suggestions": []}, {"comparison_object": "tellinoid", "suggestions": []}, {"comparison_object": "tells", "suggestions": []}, {"comparison_object": "tellsome", "suggestions": []}, {"comparison_object": "tellt", "suggestions": []}, {"comparison_object": "telltale", "suggestions": []}, {"comparison_object": "telltalely", "suggestions": []}, {"comparison_object": "telltales", "suggestions": []}, {"comparison_object": "telltruth", "suggestions": []}, {"comparison_object": "tellural", "suggestions": []}, {"comparison_object": "tellurate", "suggestions": []}, {"comparison_object": "telluret", "suggestions": []}, {"comparison_object": "tellureted", "suggestions": []}, {"comparison_object": "tellurethyl", "suggestions": []}, {"comparison_object": "telluretted", "suggestions": []}, {"comparison_object": "tellurhydric", "suggestions": []}, {"comparison_object": "tellurian", "suggestions": []}, {"comparison_object": "telluric", "suggestions": []}, {"comparison_object": "telluride", "suggestions": ["tiff"]}, {"comparison_object": "telluriferous", "suggestions": []}, {"comparison_object": "tellurion", "suggestions": []}, {"comparison_object": "tellurism", "suggestions": []}, {"comparison_object": "tellurist", "suggestions": []}, {"comparison_object": "tellurite", "suggestions": []}, {"comparison_object": "tellurium", "suggestions": []}, {"comparison_object": "tellurize", "suggestions": []}, {"comparison_object": "tellurized", "suggestions": []}, {"comparison_object": "tellurizing", "suggestions": []}, {"comparison_object": "tellurometer", "suggestions": []}, {"comparison_object": "telluronium", "suggestions": []}, {"comparison_object": "tellurous", "suggestions": []}, {"comparison_object": "tellus", "suggestions": []}, {"comparison_object": "telmatology", "suggestions": []}, {"comparison_object": "telmatological", "suggestions": []}, {"comparison_object": "teloblast", "suggestions": []}, {"comparison_object": "teloblastic", "suggestions": []}, {"comparison_object": "telocentric", "suggestions": []}, {"comparison_object": "telodendria", "suggestions": []}, {"comparison_object": "telodendrion", "suggestions": []}, {"comparison_object": "telodendron", "suggestions": []}, {"comparison_object": "telodynamic", "suggestions": []}, {"comparison_object": "teloi", "suggestions": []}, {"comparison_object": "telokinesis", "suggestions": []}, {"comparison_object": "telolecithal", "suggestions": []}, {"comparison_object": "telolemma", "suggestions": []}, {"comparison_object": "telolemmata", "suggestions": []}, {"comparison_object": "telome", "suggestions": []}, {"comparison_object": "telomerization", "suggestions": []}, {"comparison_object": "telomes", "suggestions": []}, {"comparison_object": "telomic", "suggestions": []}, {"comparison_object": "telomitic", "suggestions": []}, {"comparison_object": "telonism", "suggestions": []}, {"comparison_object": "teloogoo", "suggestions": []}, {"comparison_object": "telopea", "suggestions": []}, {"comparison_object": "telophase", "suggestions": []}, {"comparison_object": "telophasic", "suggestions": []}, {"comparison_object": "telophragma", "suggestions": []}, {"comparison_object": "telopsis", "suggestions": []}, {"comparison_object": "teloptic", "suggestions": []}, {"comparison_object": "telos", "suggestions": []}, {"comparison_object": "telosynapsis", "suggestions": []}, {"comparison_object": "telosynaptic", "suggestions": []}, {"comparison_object": "telosynaptist", "suggestions": []}, {"comparison_object": "telotaxis", "suggestions": []}, {"comparison_object": "teloteropathy", "suggestions": []}, {"comparison_object": "teloteropathic", "suggestions": []}, {"comparison_object": "teloteropathically", "suggestions": []}, {"comparison_object": "telotype", "suggestions": []}, {"comparison_object": "telotremata", "suggestions": []}, {"comparison_object": "telotrematous", "suggestions": []}, {"comparison_object": "telotroch", "suggestions": []}, {"comparison_object": "telotrocha", "suggestions": []}, {"comparison_object": "telotrochal", "suggestions": []}, {"comparison_object": "telotrochous", "suggestions": []}, {"comparison_object": "telotrophic", "suggestions": []}, {"comparison_object": "telpath", "suggestions": []}, {"comparison_object": "telpher", "suggestions": []}, {"comparison_object": "telpherage", "suggestions": []}, {"comparison_object": "telphered", "suggestions": []}, {"comparison_object": "telpheric", "suggestions": []}, {"comparison_object": "telphering", "suggestions": []}, {"comparison_object": "telpherman", "suggestions": []}, {"comparison_object": "telphermen", "suggestions": []}, {"comparison_object": "telphers", "suggestions": []}, {"comparison_object": "telpherway", "suggestions": []}, {"comparison_object": "telson", "suggestions": []}, {"comparison_object": "telsonic", "suggestions": []}, {"comparison_object": "telsons", "suggestions": []}, {"comparison_object": "telt", "suggestions": []}, {"comparison_object": "telugu", "suggestions": ["tamil", "kannada"]}, {"comparison_object": "telurgy", "suggestions": []}, {"comparison_object": "tem", "suggestions": []}, {"comparison_object": "tema", "suggestions": []}, {"comparison_object": "temacha", "suggestions": []}, {"comparison_object": "temadau", "suggestions": []}, {"comparison_object": "temalacatl", "suggestions": []}, {"comparison_object": "teman", "suggestions": []}, {"comparison_object": "temanite", "suggestions": []}, {"comparison_object": "tembe", "suggestions": []}, {"comparison_object": "tembeitera", "suggestions": []}, {"comparison_object": "tembeta", "suggestions": []}, {"comparison_object": "tembetara", "suggestions": []}, {"comparison_object": "temblor", "suggestions": []}, {"comparison_object": "temblores", "suggestions": []}, {"comparison_object": "temblors", "suggestions": []}, {"comparison_object": "tembu", "suggestions": []}, {"comparison_object": "temene", "suggestions": []}, {"comparison_object": "temenos", "suggestions": []}, {"comparison_object": "temerarious", "suggestions": []}, {"comparison_object": "temerariously", "suggestions": []}, {"comparison_object": "temerariousness", "suggestions": []}, {"comparison_object": "temerate", "suggestions": []}, {"comparison_object": "temerity", "suggestions": []}, {"comparison_object": "temerities", "suggestions": []}, {"comparison_object": "temeritous", "suggestions": []}, {"comparison_object": "temerous", "suggestions": []}, {"comparison_object": "temerously", "suggestions": []}, {"comparison_object": "temerousness", "suggestions": []}, {"comparison_object": "temescal", "suggestions": []}, {"comparison_object": "temiak", "suggestions": []}, {"comparison_object": "temin", "suggestions": []}, {"comparison_object": "temiskaming", "suggestions": []}, {"comparison_object": "temne", "suggestions": []}, {"comparison_object": "temnospondyli", "suggestions": []}, {"comparison_object": "temnospondylous", "suggestions": []}, {"comparison_object": "temp", "suggestions": ["speed", "permanent", "co2", "ss", "distance", "cursors", "lists"]}, {"comparison_object": "tempe", "suggestions": []}, {"comparison_object": "tempean", "suggestions": []}, {"comparison_object": "tempeh", "suggestions": []}, {"comparison_object": "tempehs", "suggestions": []}, {"comparison_object": "temper", "suggestions": []}, {"comparison_object": "tempera", "suggestions": ["fresco", "acrylic"]}, {"comparison_object": "temperability", "suggestions": []}, {"comparison_object": "temperable", "suggestions": []}, {"comparison_object": "temperably", "suggestions": []}, {"comparison_object": "temperality", "suggestions": []}, {"comparison_object": "temperament", "suggestions": ["stretch"]}, {"comparison_object": "temperamental", "suggestions": []}, {"comparison_object": "temperamentalist", "suggestions": []}, {"comparison_object": "temperamentally", "suggestions": []}, {"comparison_object": "temperamentalness", "suggestions": []}, {"comparison_object": "temperamented", "suggestions": []}, {"comparison_object": "temperaments", "suggestions": []}, {"comparison_object": "temperance", "suggestions": ["legalism", "prohibition"]}, {"comparison_object": "temperas", "suggestions": []}, {"comparison_object": "temperate", "suggestions": []}, {"comparison_object": "temperately", "suggestions": []}, {"comparison_object": "temperateness", "suggestions": []}, {"comparison_object": "temperative", "suggestions": []}, {"comparison_object": "temperature", "suggestions": ["heat", "activity", "resistance", "fluorescence", "pressure", "torque", "viscosity"]}, {"comparison_object": "temperatures", "suggestions": ["enthalpy"]}, {"comparison_object": "tempered", "suggestions": []}, {"comparison_object": "temperedly", "suggestions": []}, {"comparison_object": "temperedness", "suggestions": []}, {"comparison_object": "temperer", "suggestions": []}, {"comparison_object": "temperers", "suggestions": []}, {"comparison_object": "tempery", "suggestions": []}, {"comparison_object": "tempering", "suggestions": ["hardness"]}, {"comparison_object": "temperish", "suggestions": []}, {"comparison_object": "temperless", "suggestions": []}, {"comparison_object": "tempers", "suggestions": ["judas"]}, {"comparison_object": "tempersome", "suggestions": []}, {"comparison_object": "tempest", "suggestions": ["locust"]}, {"comparison_object": "tempested", "suggestions": []}, {"comparison_object": "tempesty", "suggestions": []}, {"comparison_object": "tempestical", "suggestions": []}, {"comparison_object": "tempesting", "suggestions": []}, {"comparison_object": "tempestive", "suggestions": []}, {"comparison_object": "tempestively", "suggestions": []}, {"comparison_object": "tempestivity", "suggestions": []}, {"comparison_object": "tempests", "suggestions": []}, {"comparison_object": "tempestuous", "suggestions": []}, {"comparison_object": "tempestuously", "suggestions": []}, {"comparison_object": "tempestuousness", "suggestions": []}, {"comparison_object": "tempete", "suggestions": []}, {"comparison_object": "tempi", "suggestions": []}, {"comparison_object": "tempyo", "suggestions": []}, {"comparison_object": "templar", "suggestions": ["paladin"]}, {"comparison_object": "templardom", "suggestions": []}, {"comparison_object": "templary", "suggestions": []}, {"comparison_object": "templarism", "suggestions": []}, {"comparison_object": "templarlike", "suggestions": []}, {"comparison_object": "templarlikeness", "suggestions": []}, {"comparison_object": "templars", "suggestions": ["assassins"]}, {"comparison_object": "template", "suggestions": ["custom", "platform", "page", "reality", "specialization", "structure"]}, {"comparison_object": "templater", "suggestions": []}, {"comparison_object": "templates", "suggestions": ["generics", "themes", "designers", "functions", "tiles", "stencils", "campaigns"]}, {"comparison_object": "temple", "suggestions": ["massachusetts", "mass", "umass", "kansas", "duke", "delaware", "charlotte"]}, {"comparison_object": "templed", "suggestions": []}, {"comparison_object": "templeful", "suggestions": []}, {"comparison_object": "templeless", "suggestions": []}, {"comparison_object": "templelike", "suggestions": []}, {"comparison_object": "temples", "suggestions": ["trees"]}, {"comparison_object": "templet", "suggestions": []}, {"comparison_object": "templetonia", "suggestions": []}, {"comparison_object": "templets", "suggestions": []}, {"comparison_object": "templeward", "suggestions": []}, {"comparison_object": "templize", "suggestions": []}, {"comparison_object": "templon", "suggestions": []}, {"comparison_object": "templum", "suggestions": []}, {"comparison_object": "tempo", "suggestions": ["rhythm", "pace", "distance"]}, {"comparison_object": "tempora", "suggestions": []}, {"comparison_object": "temporal", "suggestions": ["rate", "incompleteness", "lifetime"]}, {"comparison_object": "temporale", "suggestions": []}, {"comparison_object": "temporalis", "suggestions": []}, {"comparison_object": "temporalism", "suggestions": []}, {"comparison_object": "temporalist", "suggestions": []}, {"comparison_object": "temporality", "suggestions": []}, {"comparison_object": "temporalities", "suggestions": []}, {"comparison_object": "temporalize", "suggestions": []}, {"comparison_object": "temporally", "suggestions": []}, {"comparison_object": "temporalness", "suggestions": []}, {"comparison_object": "temporals", "suggestions": []}, {"comparison_object": "temporalty", "suggestions": []}, {"comparison_object": "temporalties", "suggestions": []}, {"comparison_object": "temporaneous", "suggestions": []}, {"comparison_object": "temporaneously", "suggestions": []}, {"comparison_object": "temporaneousness", "suggestions": []}, {"comparison_object": "temporary", "suggestions": ["permanent", "cirrhosis", "ownership", "detours", "brits", "implant", "static"]}, {"comparison_object": "temporaries", "suggestions": []}, {"comparison_object": "temporarily", "suggestions": []}, {"comparison_object": "temporariness", "suggestions": []}, {"comparison_object": "temporator", "suggestions": []}, {"comparison_object": "tempore", "suggestions": []}, {"comparison_object": "temporisation", "suggestions": []}, {"comparison_object": "temporise", "suggestions": []}, {"comparison_object": "temporised", "suggestions": []}, {"comparison_object": "temporiser", "suggestions": []}, {"comparison_object": "temporising", "suggestions": []}, {"comparison_object": "temporisingly", "suggestions": []}, {"comparison_object": "temporist", "suggestions": []}, {"comparison_object": "temporization", "suggestions": []}, {"comparison_object": "temporize", "suggestions": []}, {"comparison_object": "temporized", "suggestions": []}, {"comparison_object": "temporizer", "suggestions": []}, {"comparison_object": "temporizers", "suggestions": []}, {"comparison_object": "temporizes", "suggestions": []}, {"comparison_object": "temporizing", "suggestions": []}, {"comparison_object": "temporizingly", "suggestions": []}, {"comparison_object": "temporoalar", "suggestions": []}, {"comparison_object": "temporoauricular", "suggestions": []}, {"comparison_object": "temporocentral", "suggestions": []}, {"comparison_object": "temporocerebellar", "suggestions": []}, {"comparison_object": "temporofacial", "suggestions": []}, {"comparison_object": "temporofrontal", "suggestions": []}, {"comparison_object": "temporohyoid", "suggestions": []}, {"comparison_object": "temporomalar", "suggestions": []}, {"comparison_object": "temporomandibular", "suggestions": []}, {"comparison_object": "temporomastoid", "suggestions": []}, {"comparison_object": "temporomaxillary", "suggestions": []}, {"comparison_object": "temporooccipital", "suggestions": []}, {"comparison_object": "temporoparietal", "suggestions": []}, {"comparison_object": "temporopontine", "suggestions": []}, {"comparison_object": "temporosphenoid", "suggestions": []}, {"comparison_object": "temporosphenoidal", "suggestions": []}, {"comparison_object": "temporozygomatic", "suggestions": []}, {"comparison_object": "tempos", "suggestions": ["intervals"]}, {"comparison_object": "tempre", "suggestions": []}, {"comparison_object": "temprely", "suggestions": []}, {"comparison_object": "temps", "suggestions": []}, {"comparison_object": "tempt", "suggestions": []}, {"comparison_object": "temptability", "suggestions": []}, {"comparison_object": "temptable", "suggestions": []}, {"comparison_object": "temptableness", "suggestions": []}, {"comparison_object": "temptation", "suggestions": ["rationality", "self-control", "baptism", "fringe", "sin", "righteousness", "politicians"]}, {"comparison_object": "temptational", "suggestions": []}, {"comparison_object": "temptationless", "suggestions": []}, {"comparison_object": "temptations", "suggestions": ["tendencies"]}, {"comparison_object": "temptatious", "suggestions": []}, {"comparison_object": "temptatory", "suggestions": []}, {"comparison_object": "tempted", "suggestions": []}, {"comparison_object": "tempter", "suggestions": []}, {"comparison_object": "tempters", "suggestions": []}, {"comparison_object": "tempting", "suggestions": []}, {"comparison_object": "temptingly", "suggestions": []}, {"comparison_object": "temptingness", "suggestions": []}, {"comparison_object": "temptress", "suggestions": []}, {"comparison_object": "temptresses", "suggestions": []}, {"comparison_object": "tempts", "suggestions": []}, {"comparison_object": "temptsome", "suggestions": []}, {"comparison_object": "tempura", "suggestions": []}, {"comparison_object": "tempuras", "suggestions": []}, {"comparison_object": "tempus", "suggestions": []}, {"comparison_object": "temse", "suggestions": []}, {"comparison_object": "temsebread", "suggestions": []}, {"comparison_object": "temseloaf", "suggestions": []}, {"comparison_object": "temser", "suggestions": []}, {"comparison_object": "temulence", "suggestions": []}, {"comparison_object": "temulency", "suggestions": []}, {"comparison_object": "temulent", "suggestions": []}, {"comparison_object": "temulentive", "suggestions": []}, {"comparison_object": "temulently", "suggestions": []}, {"comparison_object": "ten", "suggestions": ["pit", "freshman", "jaguars", "eleven"]}, {"comparison_object": "tenability", "suggestions": []}, {"comparison_object": "tenable", "suggestions": []}, {"comparison_object": "tenableness", "suggestions": []}, {"comparison_object": "tenably", "suggestions": []}, {"comparison_object": "tenace", "suggestions": []}, {"comparison_object": "tenaces", "suggestions": []}, {"comparison_object": "tenacy", "suggestions": []}, {"comparison_object": "tenacious", "suggestions": []}, {"comparison_object": "tenaciously", "suggestions": []}, {"comparison_object": "tenaciousness", "suggestions": []}, {"comparison_object": "tenacity", "suggestions": ["talent", "iteration"]}, {"comparison_object": "tenacities", "suggestions": []}, {"comparison_object": "tenacle", "suggestions": []}, {"comparison_object": "tenacula", "suggestions": []}, {"comparison_object": "tenaculum", "suggestions": []}, {"comparison_object": "tenaculums", "suggestions": []}, {"comparison_object": "tenai", "suggestions": []}, {"comparison_object": "tenail", "suggestions": []}, {"comparison_object": "tenaille", "suggestions": []}, {"comparison_object": "tenailles", "suggestions": []}, {"comparison_object": "tenaillon", "suggestions": []}, {"comparison_object": "tenails", "suggestions": []}, {"comparison_object": "tenaim", "suggestions": []}, {"comparison_object": "tenaktak", "suggestions": []}, {"comparison_object": "tenalgia", "suggestions": []}, {"comparison_object": "tenancy", "suggestions": ["license"]}, {"comparison_object": "tenancies", "suggestions": []}, {"comparison_object": "tenant", "suggestions": ["landlord", "owner", "houseguest", "occupant", "tenet", "roommate", "lease"]}, {"comparison_object": "tenantable", "suggestions": []}, {"comparison_object": "tenantableness", "suggestions": []}, {"comparison_object": "tenanted", "suggestions": []}, {"comparison_object": "tenanter", "suggestions": []}, {"comparison_object": "tenanting", "suggestions": []}, {"comparison_object": "tenantism", "suggestions": []}, {"comparison_object": "tenantless", "suggestions": []}, {"comparison_object": "tenantlike", "suggestions": []}, {"comparison_object": "tenantry", "suggestions": []}, {"comparison_object": "tenantries", "suggestions": []}, {"comparison_object": "tenants", "suggestions": ["landlords", "owners", "lodgers", "landlord"]}, {"comparison_object": "tenantship", "suggestions": []}, {"comparison_object": "tench", "suggestions": []}, {"comparison_object": "tenches", "suggestions": []}, {"comparison_object": "tenchweed", "suggestions": []}, {"comparison_object": "tencteri", "suggestions": []}, {"comparison_object": "tend", "suggestions": []}, {"comparison_object": "tendable", "suggestions": []}, {"comparison_object": "tendance", "suggestions": []}, {"comparison_object": "tendances", "suggestions": []}, {"comparison_object": "tendant", "suggestions": []}, {"comparison_object": "tended", "suggestions": []}, {"comparison_object": "tendejon", "suggestions": []}, {"comparison_object": "tendence", "suggestions": []}, {"comparison_object": "tendences", "suggestions": []}, {"comparison_object": "tendency", "suggestions": ["implication", "trend"]}, {"comparison_object": "tendencies", "suggestions": []}, {"comparison_object": "tendencious", "suggestions": []}, {"comparison_object": "tendenciously", "suggestions": []}, {"comparison_object": "tendenciousness", "suggestions": []}, {"comparison_object": "tendent", "suggestions": []}, {"comparison_object": "tendential", "suggestions": []}, {"comparison_object": "tendentially", "suggestions": []}, {"comparison_object": "tendentious", "suggestions": []}, {"comparison_object": "tendentiously", "suggestions": []}, {"comparison_object": "tendentiousness", "suggestions": []}, {"comparison_object": "tender", "suggestions": ["tough"]}, {"comparison_object": "tenderability", "suggestions": []}, {"comparison_object": "tenderable", "suggestions": []}, {"comparison_object": "tenderably", "suggestions": []}, {"comparison_object": "tendered", "suggestions": []}, {"comparison_object": "tenderee", "suggestions": []}, {"comparison_object": "tenderer", "suggestions": []}, {"comparison_object": "tenderers", "suggestions": []}, {"comparison_object": "tenderest", "suggestions": []}, {"comparison_object": "tenderfeet", "suggestions": []}, {"comparison_object": "tenderfoot", "suggestions": []}, {"comparison_object": "tenderfootish", "suggestions": []}, {"comparison_object": "tenderfoots", "suggestions": []}, {"comparison_object": "tenderful", "suggestions": []}, {"comparison_object": "tenderfully", "suggestions": []}, {"comparison_object": "tenderheart", "suggestions": []}, {"comparison_object": "tenderhearted", "suggestions": []}, {"comparison_object": "tenderheartedly", "suggestions": []}, {"comparison_object": "tenderheartedness", "suggestions": []}, {"comparison_object": "tendering", "suggestions": []}, {"comparison_object": "tenderisation", "suggestions": []}, {"comparison_object": "tenderise", "suggestions": []}, {"comparison_object": "tenderised", "suggestions": []}, {"comparison_object": "tenderiser", "suggestions": []}, {"comparison_object": "tenderish", "suggestions": []}, {"comparison_object": "tenderising", "suggestions": []}, {"comparison_object": "tenderization", "suggestions": []}, {"comparison_object": "tenderize", "suggestions": []}, {"comparison_object": "tenderized", "suggestions": []}, {"comparison_object": "tenderizer", "suggestions": []}, {"comparison_object": "tenderizers", "suggestions": []}, {"comparison_object": "tenderizes", "suggestions": []}, {"comparison_object": "tenderizing", "suggestions": []}, {"comparison_object": "tenderly", "suggestions": []}, {"comparison_object": "tenderling", "suggestions": []}, {"comparison_object": "tenderloin", "suggestions": ["loin"]}, {"comparison_object": "tenderloins", "suggestions": []}, {"comparison_object": "tenderness", "suggestions": ["watering"]}, {"comparison_object": "tenderometer", "suggestions": []}, {"comparison_object": "tenders", "suggestions": []}, {"comparison_object": "tendersome", "suggestions": []}, {"comparison_object": "tendicle", "suggestions": []}, {"comparison_object": "tendido", "suggestions": []}, {"comparison_object": "tendinal", "suggestions": []}, {"comparison_object": "tendineal", "suggestions": []}, {"comparison_object": "tending", "suggestions": []}, {"comparison_object": "tendingly", "suggestions": []}, {"comparison_object": "tendinitis", "suggestions": []}, {"comparison_object": "tendinous", "suggestions": []}, {"comparison_object": "tendinousness", "suggestions": []}, {"comparison_object": "tendment", "suggestions": []}, {"comparison_object": "tendo", "suggestions": []}, {"comparison_object": "tendomucin", "suggestions": []}, {"comparison_object": "tendomucoid", "suggestions": []}, {"comparison_object": "tendon", "suggestions": ["muscle"]}, {"comparison_object": "tendonitis", "suggestions": []}, {"comparison_object": "tendonous", "suggestions": []}, {"comparison_object": "tendons", "suggestions": []}, {"comparison_object": "tendoor", "suggestions": []}, {"comparison_object": "tendoplasty", "suggestions": []}, {"comparison_object": "tendosynovitis", "suggestions": []}, {"comparison_object": "tendotome", "suggestions": []}, {"comparison_object": "tendotomy", "suggestions": []}, {"comparison_object": "tendour", "suggestions": []}, {"comparison_object": "tendovaginal", "suggestions": []}, {"comparison_object": "tendovaginitis", "suggestions": []}, {"comparison_object": "tendrac", "suggestions": []}, {"comparison_object": "tendre", "suggestions": []}, {"comparison_object": "tendrel", "suggestions": []}, {"comparison_object": "tendresse", "suggestions": []}, {"comparison_object": "tendry", "suggestions": []}, {"comparison_object": "tendril", "suggestions": []}, {"comparison_object": "tendriled", "suggestions": []}, {"comparison_object": "tendriliferous", "suggestions": []}, {"comparison_object": "tendrillar", "suggestions": []}, {"comparison_object": "tendrilled", "suggestions": []}, {"comparison_object": "tendrilly", "suggestions": []}, {"comparison_object": "tendrilous", "suggestions": []}, {"comparison_object": "tendrils", "suggestions": []}, {"comparison_object": "tendron", "suggestions": []}, {"comparison_object": "tends", "suggestions": []}, {"comparison_object": "tenebra", "suggestions": []}, {"comparison_object": "tenebrae", "suggestions": []}, {"comparison_object": "tenebres", "suggestions": []}, {"comparison_object": "tenebricose", "suggestions": []}, {"comparison_object": "tenebrific", "suggestions": []}, {"comparison_object": "tenebrificate", "suggestions": []}, {"comparison_object": "tenebrio", "suggestions": []}, {"comparison_object": "tenebrion", "suggestions": []}, {"comparison_object": "tenebrionid", "suggestions": []}, {"comparison_object": "tenebrionidae", "suggestions": []}, {"comparison_object": "tenebrious", "suggestions": []}, {"comparison_object": "tenebriously", "suggestions": []}, {"comparison_object": "tenebriousness", "suggestions": []}, {"comparison_object": "tenebrism", "suggestions": []}, {"comparison_object": "tenebrist", "suggestions": []}, {"comparison_object": "tenebrity", "suggestions": []}, {"comparison_object": "tenebrose", "suggestions": []}, {"comparison_object": "tenebrosi", "suggestions": []}, {"comparison_object": "tenebrosity", "suggestions": []}, {"comparison_object": "tenebrous", "suggestions": []}, {"comparison_object": "tenebrously", "suggestions": []}, {"comparison_object": "tenebrousness", "suggestions": []}, {"comparison_object": "tenectomy", "suggestions": []}, {"comparison_object": "tenement", "suggestions": []}, {"comparison_object": "tenemental", "suggestions": []}, {"comparison_object": "tenementary", "suggestions": []}, {"comparison_object": "tenemented", "suggestions": []}, {"comparison_object": "tenementer", "suggestions": []}, {"comparison_object": "tenementization", "suggestions": []}, {"comparison_object": "tenementize", "suggestions": []}, {"comparison_object": "tenements", "suggestions": []}, {"comparison_object": "tenementum", "suggestions": []}, {"comparison_object": "tenenda", "suggestions": []}, {"comparison_object": "tenendas", "suggestions": []}, {"comparison_object": "tenendum", "suggestions": []}, {"comparison_object": "tenent", "suggestions": []}, {"comparison_object": "teneral", "suggestions": []}, {"comparison_object": "teneramente", "suggestions": []}, {"comparison_object": "teneriffe", "suggestions": []}, {"comparison_object": "tenerity", "suggestions": []}, {"comparison_object": "tenesmic", "suggestions": []}, {"comparison_object": "tenesmus", "suggestions": []}, {"comparison_object": "tenesmuses", "suggestions": []}, {"comparison_object": "tenet", "suggestions": ["tenant", "rice"]}, {"comparison_object": "tenets", "suggestions": []}, {"comparison_object": "tenez", "suggestions": []}, {"comparison_object": "tenfold", "suggestions": []}, {"comparison_object": "tenfoldness", "suggestions": []}]