[{"comparison_object": "anguishes", "suggestions": []}, {"comparison_object": "anguishful", "suggestions": []}, {"comparison_object": "anguishing", "suggestions": []}, {"comparison_object": "anguishous", "suggestions": []}, {"comparison_object": "anguishously", "suggestions": []}, {"comparison_object": "angula", "suggestions": []}, {"comparison_object": "angular", "suggestions": []}, {"comparison_object": "angulare", "suggestions": []}, {"comparison_object": "angularia", "suggestions": []}, {"comparison_object": "angularity", "suggestions": ["curvature"]}, {"comparison_object": "angularities", "suggestions": []}, {"comparison_object": "angularization", "suggestions": []}, {"comparison_object": "angularize", "suggestions": []}, {"comparison_object": "angularly", "suggestions": []}, {"comparison_object": "angularness", "suggestions": []}, {"comparison_object": "angulate", "suggestions": []}, {"comparison_object": "angulated", "suggestions": []}, {"comparison_object": "angulately", "suggestions": []}, {"comparison_object": "angulateness", "suggestions": []}, {"comparison_object": "angulates", "suggestions": []}, {"comparison_object": "angulating", "suggestions": []}, {"comparison_object": "angulation", "suggestions": []}, {"comparison_object": "angulatogibbous", "suggestions": []}, {"comparison_object": "angulatosinuous", "suggestions": []}, {"comparison_object": "angule", "suggestions": []}, {"comparison_object": "anguliferous", "suggestions": []}, {"comparison_object": "angulinerved", "suggestions": []}, {"comparison_object": "anguloa", "suggestions": []}, {"comparison_object": "angulodentate", "suggestions": []}, {"comparison_object": "angulometer", "suggestions": []}, {"comparison_object": "angulose", "suggestions": []}, {"comparison_object": "angulosity", "suggestions": []}, {"comparison_object": "angulosplenial", "suggestions": []}, {"comparison_object": "angulous", "suggestions": []}, {"comparison_object": "angulus", "suggestions": []}, {"comparison_object": "anguria", "suggestions": []}, {"comparison_object": "angus", "suggestions": ["hereford", "penelope"]}, {"comparison_object": "anguses", "suggestions": []}, {"comparison_object": "angust", "suggestions": []}, {"comparison_object": "angustate", "suggestions": []}, {"comparison_object": "angustia", "suggestions": []}, {"comparison_object": "angusticlave", "suggestions": []}, {"comparison_object": "angustifoliate", "suggestions": []}, {"comparison_object": "angustifolious", "suggestions": []}, {"comparison_object": "angustirostrate", "suggestions": []}, {"comparison_object": "angustisellate", "suggestions": []}, {"comparison_object": "angustiseptal", "suggestions": []}, {"comparison_object": "angustiseptate", "suggestions": []}, {"comparison_object": "angustura", "suggestions": []}, {"comparison_object": "angwantibo", "suggestions": []}, {"comparison_object": "angwich", "suggestions": []}, {"comparison_object": "anhaematopoiesis", "suggestions": []}, {"comparison_object": "anhaematosis", "suggestions": []}, {"comparison_object": "anhaemolytic", "suggestions": []}, {"comparison_object": "anhalamine", "suggestions": []}, {"comparison_object": "anhaline", "suggestions": []}, {"comparison_object": "anhalonidine", "suggestions": []}, {"comparison_object": "anhalonin", "suggestions": []}, {"comparison_object": "anhalonine", "suggestions": []}, {"comparison_object": "anhalonium", "suggestions": []}, {"comparison_object": "anhalouidine", "suggestions": []}, {"comparison_object": "anhang", "suggestions": []}, {"comparison_object": "anhanga", "suggestions": []}, {"comparison_object": "anharmonic", "suggestions": []}, {"comparison_object": "anhedonia", "suggestions": ["reinforcement"]}, {"comparison_object": "anhedonic", "suggestions": []}, {"comparison_object": "anhedral", "suggestions": []}, {"comparison_object": "anhedron", "suggestions": []}, {"comparison_object": "anhelation", "suggestions": []}, {"comparison_object": "anhele", "suggestions": []}, {"comparison_object": "anhelose", "suggestions": []}, {"comparison_object": "anhelous", "suggestions": []}, {"comparison_object": "anhematopoiesis", "suggestions": []}, {"comparison_object": "anhematosis", "suggestions": []}, {"comparison_object": "anhemitonic", "suggestions": []}, {"comparison_object": "anhemolytic", "suggestions": []}, {"comparison_object": "anhyd", "suggestions": []}, {"comparison_object": "anhydraemia", "suggestions": []}, {"comparison_object": "anhydraemic", "suggestions": []}, {"comparison_object": "anhydrate", "suggestions": []}, {"comparison_object": "anhydrated", "suggestions": []}, {"comparison_object": "anhydrating", "suggestions": []}, {"comparison_object": "anhydration", "suggestions": []}, {"comparison_object": "anhydremia", "suggestions": []}, {"comparison_object": "anhydremic", "suggestions": []}, {"comparison_object": "anhydric", "suggestions": []}, {"comparison_object": "anhydride", "suggestions": []}, {"comparison_object": "anhydrides", "suggestions": []}, {"comparison_object": "anhydridization", "suggestions": []}, {"comparison_object": "anhydridize", "suggestions": []}, {"comparison_object": "anhydrite", "suggestions": []}, {"comparison_object": "anhydrization", "suggestions": []}, {"comparison_object": "anhydrize", "suggestions": []}, {"comparison_object": "anhydroglocose", "suggestions": []}, {"comparison_object": "anhydromyelia", "suggestions": []}, {"comparison_object": "anhidrosis", "suggestions": []}, {"comparison_object": "anhydrosis", "suggestions": []}, {"comparison_object": "anhidrotic", "suggestions": []}, {"comparison_object": "anhydrotic", "suggestions": []}, {"comparison_object": "anhydrous", "suggestions": []}, {"comparison_object": "anhydrously", "suggestions": []}, {"comparison_object": "anhydroxime", "suggestions": []}, {"comparison_object": "anhima", "suggestions": []}, {"comparison_object": "anhimae", "suggestions": []}, {"comparison_object": "anhimidae", "suggestions": []}, {"comparison_object": "anhinga", "suggestions": []}, {"comparison_object": "anhingas", "suggestions": []}, {"comparison_object": "anhysteretic", "suggestions": []}, {"comparison_object": "anhistic", "suggestions": []}, {"comparison_object": "anhistous", "suggestions": []}, {"comparison_object": "anhungered", "suggestions": []}, {"comparison_object": "anhungry", "suggestions": []}, {"comparison_object": "ani", "suggestions": ["obi", "ditty", "math"]}, {"comparison_object": "any", "suggestions": []}, {"comparison_object": "aniba", "suggestions": []}, {"comparison_object": "anybody", "suggestions": []}, {"comparison_object": "anybodyd", "suggestions": []}, {"comparison_object": "anybodies", "suggestions": []}, {"comparison_object": "anicca", "suggestions": []}, {"comparison_object": "anice", "suggestions": []}, {"comparison_object": "anychia", "suggestions": []}, {"comparison_object": "aniconic", "suggestions": []}, {"comparison_object": "aniconism", "suggestions": []}, {"comparison_object": "anicular", "suggestions": []}, {"comparison_object": "anicut", "suggestions": []}, {"comparison_object": "anidian", "suggestions": []}, {"comparison_object": "anidiomatic", "suggestions": []}, {"comparison_object": "anidiomatical", "suggestions": []}, {"comparison_object": "anidrosis", "suggestions": []}, {"comparison_object": "aniellidae", "suggestions": []}, {"comparison_object": "aniente", "suggestions": []}, {"comparison_object": "anientise", "suggestions": []}, {"comparison_object": "anigh", "suggestions": []}, {"comparison_object": "anight", "suggestions": []}, {"comparison_object": "anights", "suggestions": []}, {"comparison_object": "anyhow", "suggestions": []}, {"comparison_object": "anil", "suggestions": []}, {"comparison_object": "anilao", "suggestions": []}, {"comparison_object": "anilau", "suggestions": []}, {"comparison_object": "anile", "suggestions": []}, {"comparison_object": "anileness", "suggestions": []}, {"comparison_object": "anilic", "suggestions": []}, {"comparison_object": "anilid", "suggestions": []}, {"comparison_object": "anilide", "suggestions": []}, {"comparison_object": "anilidic", "suggestions": []}, {"comparison_object": "anilidoxime", "suggestions": []}, {"comparison_object": "aniliid", "suggestions": []}, {"comparison_object": "anilin", "suggestions": []}, {"comparison_object": "anilinctus", "suggestions": []}, {"comparison_object": "aniline", "suggestions": []}, {"comparison_object": "anilines", "suggestions": []}, {"comparison_object": "anilingus", "suggestions": []}, {"comparison_object": "anilinism", "suggestions": []}, {"comparison_object": "anilino", "suggestions": []}, {"comparison_object": "anilinophile", "suggestions": []}, {"comparison_object": "anilinophilous", "suggestions": []}, {"comparison_object": "anilins", "suggestions": []}, {"comparison_object": "anility", "suggestions": []}, {"comparison_object": "anilities", "suggestions": []}, {"comparison_object": "anilla", "suggestions": []}, {"comparison_object": "anilopyrin", "suggestions": []}, {"comparison_object": "anilopyrine", "suggestions": []}, {"comparison_object": "anils", "suggestions": []}, {"comparison_object": "anim", "suggestions": []}, {"comparison_object": "anima", "suggestions": ["animus"]}, {"comparison_object": "animability", "suggestions": []}, {"comparison_object": "animable", "suggestions": []}, {"comparison_object": "animableness", "suggestions": []}, {"comparison_object": "animacule", "suggestions": []}, {"comparison_object": "animadversal", "suggestions": []}, {"comparison_object": "animadversion", "suggestions": []}, {"comparison_object": "animadversional", "suggestions": []}, {"comparison_object": "animadversions", "suggestions": []}, {"comparison_object": "animadversive", "suggestions": []}, {"comparison_object": "animadversiveness", "suggestions": []}, {"comparison_object": "animadvert", "suggestions": []}, {"comparison_object": "animadverted", "suggestions": []}, {"comparison_object": "animadverter", "suggestions": []}, {"comparison_object": "animadverting", "suggestions": []}, {"comparison_object": "animadverts", "suggestions": []}, {"comparison_object": "animal", "suggestions": ["car", "vegetarian", "hawk", "bicyclist", "slater", "beast", "hunter"]}, {"comparison_object": "animala", "suggestions": []}, {"comparison_object": "animalcula", "suggestions": []}, {"comparison_object": "animalculae", "suggestions": []}, {"comparison_object": "animalcular", "suggestions": []}, {"comparison_object": "animalcule", "suggestions": []}, {"comparison_object": "animalcules", "suggestions": []}, {"comparison_object": "animalculine", "suggestions": []}, {"comparison_object": "animalculism", "suggestions": []}, {"comparison_object": "animalculist", "suggestions": []}, {"comparison_object": "animalculous", "suggestions": []}, {"comparison_object": "animalculum", "suggestions": []}, {"comparison_object": "animalhood", "suggestions": []}, {"comparison_object": "animalia", "suggestions": []}, {"comparison_object": "animalian", "suggestions": []}, {"comparison_object": "animalic", "suggestions": []}, {"comparison_object": "animalier", "suggestions": []}, {"comparison_object": "animalillio", "suggestions": []}, {"comparison_object": "animalisation", "suggestions": []}, {"comparison_object": "animalise", "suggestions": []}, {"comparison_object": "animalised", "suggestions": []}, {"comparison_object": "animalish", "suggestions": []}, {"comparison_object": "animalising", "suggestions": []}, {"comparison_object": "animalism", "suggestions": []}, {"comparison_object": "animalist", "suggestions": []}, {"comparison_object": "animalistic", "suggestions": []}, {"comparison_object": "animality", "suggestions": []}, {"comparison_object": "animalities", "suggestions": []}, {"comparison_object": "animalivora", "suggestions": []}, {"comparison_object": "animalivore", "suggestions": []}, {"comparison_object": "animalivorous", "suggestions": []}, {"comparison_object": "animalization", "suggestions": []}, {"comparison_object": "animalize", "suggestions": []}, {"comparison_object": "animalized", "suggestions": []}, {"comparison_object": "animalizing", "suggestions": []}, {"comparison_object": "animally", "suggestions": []}, {"comparison_object": "animallike", "suggestions": []}, {"comparison_object": "animalness", "suggestions": []}, {"comparison_object": "animals", "suggestions": ["humans", "plants", "zombies", "taste", "furniture", "robots", "authorities"]}, {"comparison_object": "animando", "suggestions": []}, {"comparison_object": "animant", "suggestions": []}, {"comparison_object": "animas", "suggestions": []}, {"comparison_object": "animastic", "suggestions": []}, {"comparison_object": "animastical", "suggestions": []}, {"comparison_object": "animate", "suggestions": ["illustrate"]}, {"comparison_object": "animated", "suggestions": ["film"]}, {"comparison_object": "animatedly", "suggestions": []}, {"comparison_object": "animately", "suggestions": []}, {"comparison_object": "animateness", "suggestions": []}, {"comparison_object": "animater", "suggestions": []}, {"comparison_object": "animaters", "suggestions": []}, {"comparison_object": "animates", "suggestions": []}, {"comparison_object": "animating", "suggestions": []}, {"comparison_object": "animatingly", "suggestions": []}, {"comparison_object": "animation", "suggestions": ["animator", "actors", "animations", "video", "modeling", "textbooks", "art"]}, {"comparison_object": "animations", "suggestions": ["transitions", "applets", "stills", "animation"]}, {"comparison_object": "animatism", "suggestions": []}, {"comparison_object": "animatist", "suggestions": []}, {"comparison_object": "animatistic", "suggestions": []}, {"comparison_object": "animative", "suggestions": []}, {"comparison_object": "animato", "suggestions": []}, {"comparison_object": "animatograph", "suggestions": []}, {"comparison_object": "animator", "suggestions": ["animation", "cartoonist"]}, {"comparison_object": "animators", "suggestions": ["euphoria", "earthquakes", "cartoonists"]}, {"comparison_object": "anime", "suggestions": ["cartoon", "comics", "translation", "darpa", "video", "real", "realism"]}, {"comparison_object": "animes", "suggestions": []}, {"comparison_object": "animetta", "suggestions": []}, {"comparison_object": "animi", "suggestions": []}, {"comparison_object": "animikean", "suggestions": []}, {"comparison_object": "animikite", "suggestions": []}, {"comparison_object": "animine", "suggestions": []}, {"comparison_object": "animis", "suggestions": []}, {"comparison_object": "animism", "suggestions": []}, {"comparison_object": "animisms", "suggestions": []}, {"comparison_object": "animist", "suggestions": []}, {"comparison_object": "animistic", "suggestions": []}, {"comparison_object": "animists", "suggestions": []}, {"comparison_object": "animize", "suggestions": []}, {"comparison_object": "animized", "suggestions": []}, {"comparison_object": "animo", "suggestions": []}, {"comparison_object": "anymore", "suggestions": []}, {"comparison_object": "animose", "suggestions": []}, {"comparison_object": "animoseness", "suggestions": []}, {"comparison_object": "animosity", "suggestions": []}, {"comparison_object": "animosities", "suggestions": []}, {"comparison_object": "animoso", "suggestions": []}, {"comparison_object": "animotheism", "suggestions": []}, {"comparison_object": "animous", "suggestions": []}, {"comparison_object": "animus", "suggestions": ["anima"]}, {"comparison_object": "animuses", "suggestions": []}, {"comparison_object": "anion", "suggestions": ["cation"]}, {"comparison_object": "anyone", "suggestions": []}, {"comparison_object": "anionic", "suggestions": []}, {"comparison_object": "anionically", "suggestions": []}, {"comparison_object": "anionics", "suggestions": []}, {"comparison_object": "anions", "suggestions": []}, {"comparison_object": "anyplace", "suggestions": []}, {"comparison_object": "aniridia", "suggestions": []}, {"comparison_object": "anis", "suggestions": []}, {"comparison_object": "anisado", "suggestions": []}, {"comparison_object": "anisal", "suggestions": []}, {"comparison_object": "anisalcohol", "suggestions": []}, {"comparison_object": "anisaldehyde", "suggestions": []}, {"comparison_object": "anisaldoxime", "suggestions": []}, {"comparison_object": "anisamide", "suggestions": []}, {"comparison_object": "anisandrous", "suggestions": []}, {"comparison_object": "anisanilide", "suggestions": []}, {"comparison_object": "anisanthous", "suggestions": []}, {"comparison_object": "anisate", "suggestions": []}, {"comparison_object": "anisated", "suggestions": []}, {"comparison_object": "anischuria", "suggestions": []}, {"comparison_object": "anise", "suggestions": ["anisette", "fennel"]}, {"comparison_object": "aniseed", "suggestions": []}, {"comparison_object": "aniseeds", "suggestions": []}, {"comparison_object": "aniseikonia", "suggestions": []}, {"comparison_object": "aniseikonic", "suggestions": []}, {"comparison_object": "aniselike", "suggestions": []}, {"comparison_object": "aniseroot", "suggestions": []}, {"comparison_object": "anises", "suggestions": []}, {"comparison_object": "anisette", "suggestions": ["anise"]}, {"comparison_object": "anisettes", "suggestions": []}, {"comparison_object": "anisic", "suggestions": []}, {"comparison_object": "anisidin", "suggestions": []}, {"comparison_object": "anisidine", "suggestions": []}, {"comparison_object": "anisidino", "suggestions": []}, {"comparison_object": "anisil", "suggestions": []}, {"comparison_object": "anisyl", "suggestions": []}, {"comparison_object": "anisilic", "suggestions": []}, {"comparison_object": "anisylidene", "suggestions": []}, {"comparison_object": "anisobranchiate", "suggestions": []}, {"comparison_object": "anisocarpic", "suggestions": []}, {"comparison_object": "anisocarpous", "suggestions": []}, {"comparison_object": "anisocercal", "suggestions": []}, {"comparison_object": "anisochromatic", "suggestions": []}, {"comparison_object": "anisochromia", "suggestions": []}, {"comparison_object": "anisocycle", "suggestions": []}, {"comparison_object": "anisocytosis", "suggestions": []}, {"comparison_object": "anisocoria", "suggestions": []}, {"comparison_object": "anisocotyledonous", "suggestions": []}, {"comparison_object": "anisocotyly", "suggestions": []}, {"comparison_object": "anisocratic", "suggestions": []}, {"comparison_object": "anisodactyl", "suggestions": []}, {"comparison_object": "anisodactyla", "suggestions": []}, {"comparison_object": "anisodactyle", "suggestions": []}, {"comparison_object": "anisodactyli", "suggestions": []}, {"comparison_object": "anisodactylic", "suggestions": []}, {"comparison_object": "anisodactylous", "suggestions": []}, {"comparison_object": "anisodont", "suggestions": []}, {"comparison_object": "anisogamete", "suggestions": []}, {"comparison_object": "anisogametes", "suggestions": []}, {"comparison_object": "anisogametic", "suggestions": []}, {"comparison_object": "anisogamy", "suggestions": []}, {"comparison_object": "anisogamic", "suggestions": []}, {"comparison_object": "anisogamous", "suggestions": []}, {"comparison_object": "anisogeny", "suggestions": []}, {"comparison_object": "anisogenous", "suggestions": []}, {"comparison_object": "anisogynous", "suggestions": []}, {"comparison_object": "anisognathism", "suggestions": []}, {"comparison_object": "anisognathous", "suggestions": []}, {"comparison_object": "anisoiconia", "suggestions": []}, {"comparison_object": "anisoyl", "suggestions": []}, {"comparison_object": "anisoin", "suggestions": []}, {"comparison_object": "anisokonia", "suggestions": []}, {"comparison_object": "anisol", "suggestions": []}, {"comparison_object": "anisole", "suggestions": []}, {"comparison_object": "anisoles", "suggestions": []}, {"comparison_object": "anisoleucocytosis", "suggestions": []}, {"comparison_object": "anisomeles", "suggestions": []}, {"comparison_object": "anisomelia", "suggestions": []}, {"comparison_object": "anisomelus", "suggestions": []}, {"comparison_object": "anisomeric", "suggestions": []}, {"comparison_object": "anisomerous", "suggestions": []}, {"comparison_object": "anisometric", "suggestions": []}, {"comparison_object": "anisometrope", "suggestions": []}, {"comparison_object": "anisometropia", "suggestions": []}, {"comparison_object": "anisometropic", "suggestions": []}, {"comparison_object": "anisomyarian", "suggestions": []}, {"comparison_object": "anisomyodi", "suggestions": []}, {"comparison_object": "anisomyodian", "suggestions": []}, {"comparison_object": "anisomyodous", "suggestions": []}, {"comparison_object": "anisopetalous", "suggestions": []}, {"comparison_object": "anisophylly", "suggestions": []}, {"comparison_object": "anisophyllous", "suggestions": []}, {"comparison_object": "anisopia", "suggestions": []}, {"comparison_object": "anisopleural", "suggestions": []}, {"comparison_object": "anisopleurous", "suggestions": []}, {"comparison_object": "anisopod", "suggestions": []}, {"comparison_object": "anisopoda", "suggestions": []}, {"comparison_object": "anisopodal", "suggestions": []}, {"comparison_object": "anisopodous", "suggestions": []}, {"comparison_object": "anisopogonous", "suggestions": []}, {"comparison_object": "anisoptera", "suggestions": []}, {"comparison_object": "anisopteran", "suggestions": []}, {"comparison_object": "anisopterous", "suggestions": []}, {"comparison_object": "anisosepalous", "suggestions": []}, {"comparison_object": "anisospore", "suggestions": []}, {"comparison_object": "anisostaminous", "suggestions": []}, {"comparison_object": "anisostemonous", "suggestions": []}, {"comparison_object": "anisosthenic", "suggestions": []}, {"comparison_object": "anisostichous", "suggestions": []}, {"comparison_object": "anisostichus", "suggestions": []}, {"comparison_object": "anisostomous", "suggestions": []}, {"comparison_object": "anisotonic", "suggestions": []}, {"comparison_object": "anisotropal", "suggestions": []}, {"comparison_object": "anisotrope", "suggestions": []}, {"comparison_object": "anisotropy", "suggestions": []}, {"comparison_object": "anisotropic", "suggestions": []}, {"comparison_object": "anisotropical", "suggestions": []}, {"comparison_object": "anisotropically", "suggestions": []}, {"comparison_object": "anisotropies", "suggestions": []}, {"comparison_object": "anisotropism", "suggestions": []}, {"comparison_object": "anisotropous", "suggestions": []}, {"comparison_object": "anystidae", "suggestions": []}, {"comparison_object": "anisum", "suggestions": []}, {"comparison_object": "anisuria", "suggestions": []}, {"comparison_object": "anita", "suggestions": []}, {"comparison_object": "anither", "suggestions": []}, {"comparison_object": "anything", "suggestions": []}, {"comparison_object": "anythingarian", "suggestions": []}, {"comparison_object": "anythingarianism", "suggestions": []}, {"comparison_object": "anythings", "suggestions": []}, {"comparison_object": "anytime", "suggestions": []}, {"comparison_object": "anitinstitutionalism", "suggestions": []}, {"comparison_object": "anitos", "suggestions": []}, {"comparison_object": "anitrogenous", "suggestions": []}, {"comparison_object": "anyway", "suggestions": []}, {"comparison_object": "anyways", "suggestions": []}, {"comparison_object": "anywhen", "suggestions": []}, {"comparison_object": "anywhence", "suggestions": []}, {"comparison_object": "anywhere", "suggestions": []}, {"comparison_object": "anywhereness", "suggestions": []}, {"comparison_object": "anywheres", "suggestions": []}, {"comparison_object": "anywhy", "suggestions": []}, {"comparison_object": "anywhither", "suggestions": []}, {"comparison_object": "anywise", "suggestions": []}, {"comparison_object": "anywither", "suggestions": []}, {"comparison_object": "anjan", "suggestions": []}, {"comparison_object": "anjou", "suggestions": []}, {"comparison_object": "ankara", "suggestions": []}, {"comparison_object": "ankaramite", "suggestions": []}, {"comparison_object": "ankaratrite", "suggestions": []}, {"comparison_object": "ankee", "suggestions": []}, {"comparison_object": "anker", "suggestions": []}, {"comparison_object": "ankerhold", "suggestions": []}, {"comparison_object": "ankerite", "suggestions": []}, {"comparison_object": "ankerites", "suggestions": []}, {"comparison_object": "ankh", "suggestions": []}, {"comparison_object": "ankhs", "suggestions": []}, {"comparison_object": "ankylenteron", "suggestions": []}, {"comparison_object": "ankyloblepharon", "suggestions": []}, {"comparison_object": "ankylocheilia", "suggestions": []}, {"comparison_object": "ankylodactylia", "suggestions": []}, {"comparison_object": "ankylodontia", "suggestions": []}, {"comparison_object": "ankyloglossia", "suggestions": []}, {"comparison_object": "ankylomele", "suggestions": []}, {"comparison_object": "ankylomerism", "suggestions": []}, {"comparison_object": "ankylophobia", "suggestions": []}, {"comparison_object": "ankylopodia", "suggestions": []}, {"comparison_object": "ankylopoietic", "suggestions": []}, {"comparison_object": "ankyloproctia", "suggestions": []}, {"comparison_object": "ankylorrhinia", "suggestions": []}, {"comparison_object": "ankylos", "suggestions": []}, {"comparison_object": "ankylosaur", "suggestions": []}, {"comparison_object": "ankylosaurus", "suggestions": ["velociraptor"]}, {"comparison_object": "ankylose", "suggestions": []}, {"comparison_object": "ankylosed", "suggestions": []}, {"comparison_object": "ankyloses", "suggestions": []}, {"comparison_object": "ankylosing", "suggestions": []}, {"comparison_object": "ankylosis", "suggestions": []}, {"comparison_object": "ankylostoma", "suggestions": []}, {"comparison_object": "ankylostomiasis", "suggestions": []}, {"comparison_object": "ankylotia", "suggestions": []}, {"comparison_object": "ankylotic", "suggestions": []}, {"comparison_object": "ankylotome", "suggestions": []}, {"comparison_object": "ankylotomy", "suggestions": []}, {"comparison_object": "ankylurethria", "suggestions": []}, {"comparison_object": "ankyroid", "suggestions": []}, {"comparison_object": "ankle", "suggestions": []}, {"comparison_object": "anklebone", "suggestions": []}, {"comparison_object": "anklebones", "suggestions": []}, {"comparison_object": "anklejack", "suggestions": []}, {"comparison_object": "ankles", "suggestions": []}, {"comparison_object": "anklet", "suggestions": []}, {"comparison_object": "anklets", "suggestions": []}, {"comparison_object": "anklong", "suggestions": []}, {"comparison_object": "anklung", "suggestions": []}, {"comparison_object": "ankoli", "suggestions": []}, {"comparison_object": "ankou", "suggestions": []}, {"comparison_object": "ankus", "suggestions": []}, {"comparison_object": "ankuses", "suggestions": []}, {"comparison_object": "ankush", "suggestions": []}, {"comparison_object": "ankusha", "suggestions": []}, {"comparison_object": "ankushes", "suggestions": []}, {"comparison_object": "anlace", "suggestions": []}, {"comparison_object": "anlaces", "suggestions": []}, {"comparison_object": "anlage", "suggestions": []}, {"comparison_object": "anlagen", "suggestions": []}, {"comparison_object": "anlages", "suggestions": []}, {"comparison_object": "anlas", "suggestions": []}, {"comparison_object": "anlases", "suggestions": []}, {"comparison_object": "anlaut", "suggestions": []}, {"comparison_object": "anlaute", "suggestions": []}, {"comparison_object": "anlet", "suggestions": []}, {"comparison_object": "anlia", "suggestions": []}, {"comparison_object": "anmia", "suggestions": []}, {"comparison_object": "ann", "suggestions": []}, {"comparison_object": "anna", "suggestions": ["ana", "erica", "venus", "centre", "morgan"]}, {"comparison_object": "annabel", "suggestions": []}, {"comparison_object": "annabergite", "suggestions": []}, {"comparison_object": "annal", "suggestions": []}, {"comparison_object": "annale", "suggestions": []}, {"comparison_object": "annaly", "suggestions": []}, {"comparison_object": "annalia", "suggestions": []}, {"comparison_object": "annaline", "suggestions": []}, {"comparison_object": "annalism", "suggestions": []}, {"comparison_object": "annalist", "suggestions": []}, {"comparison_object": "annalistic", "suggestions": []}, {"comparison_object": "annalistically", "suggestions": []}, {"comparison_object": "annalists", "suggestions": []}]